{
"type": "FeatureCollection",
"name": "JENIS_SDA_Baja",
"crs": { "type": "name", "properties": { "name": "urn:ogc:def:crs:OGC:1.3:CRS84" } },
"features": [
{ "type": "Feature", "properties": { "JENIS_SDA": "Baja", "LOKASI": null }, "geometry": { "type": "Point", "coordinates": [ 106.057603670809883, -5.923294596977922 ] } }
]
}
