{
"type": "FeatureCollection",
"name": "JENIS_SDA_Emas dan Perak",
"crs": { "type": "name", "properties": { "name": "urn:ogc:def:crs:OGC:1.3:CRS84" } },
"features": [
{ "type": "Feature", "properties": { "JENIS_SDA": "Emas dan Perak", "LOKASI": "Melaboh" }, "geometry": { "type": "Point", "coordinates": [ 96.152431691484992, 4.3332642508648 ] } },
{ "type": "Feature", "properties": { "JENIS_SDA": "Emas dan Perak", "LOKASI": null }, "geometry": { "type": "Point", "coordinates": [ 102.700724862394168, -3.265824578704925 ] } },
{ "type": "Feature", "properties": { "JENIS_SDA": "Emas dan Perak", "LOKASI": null }, "geometry": { "type": "Point", "coordinates": [ 106.444884299323746, -6.848024246479753 ] } },
{ "type": "Feature", "properties": { "JENIS_SDA": "Emas dan Perak", "LOKASI": "Pulau Buton" }, "geometry": { "type": "Point", "coordinates": [ 122.92230714353154, -5.052244141191171 ] } },
{ "type": "Feature", "properties": { "JENIS_SDA": "Emas dan Perak", "LOKASI": null }, "geometry": { "type": "Point", "coordinates": [ 123.199817947147409, 0.700770453338778 ] } },
{ "type": "Feature", "properties": { "JENIS_SDA": "Emas dan Perak", "LOKASI": null }, "geometry": { "type": "Point", "coordinates": [ 117.274229929315794, 0.453005198862901 ] } },
{ "type": "Feature", "properties": { "JENIS_SDA": "Emas dan Perak", "LOKASI": null }, "geometry": { "type": "Point", "coordinates": [ 104.910766535135821, -5.194860469695438 ] } },
{ "type": "Feature", "properties": { "JENIS_SDA": "Emas dan Perak", "LOKASI": "Tembagapura" }, "geometry": { "type": "Point", "coordinates": [ 136.861656896318692, -3.886156230656504 ] } }
]
}
