{
"type": "FeatureCollection",
"name": "JENIS_SDA_Tembaga",
"crs": { "type": "name", "properties": { "name": "urn:ogc:def:crs:OGC:1.3:CRS84" } },
"features": [
{ "type": "Feature", "properties": { "JENIS_SDA": "Tembaga", "LOKASI": null }, "geometry": { "type": "Point", "coordinates": [ 102.318717127540381, -2.304554144934424 ] } },
{ "type": "Feature", "properties": { "JENIS_SDA": "Tembaga", "LOKASI": null }, "geometry": { "type": "Point", "coordinates": [ 106.262121328357381, -6.789957979290654 ] } }
]
}
